{"lastSync":1745881426030,"files":{".obsidian/github-sync-metadata.json":{"path":".obsidian/github-sync-metadata.json","sha":"c00e3a6d0bcc070b4562cb516745fd6f666bc5e3","dirty":false,"justDownloaded":false,"lastModified":1745838277686},"Untitled.md":{"path":"Untitled.md","sha":null,"dirty":true,"justDownloaded":false,"lastModified":1745880935481,"deleted":true,"deletedAt":1745880941310},"Session 0.md":{"path":"Session 0.md","sha":"aaa3cb55726739e8812f5f4f53115fb3bd3f2d48","dirty":true,"justDownloaded":false,"lastModified":1745881381790},"Characters/Untitled.md":{"path":"Characters/Untitled.md","sha":null,"dirty":true,"justDownloaded":false,"lastModified":1745880948515,"deleted":true,"deletedAt":1745880957021},"Characters/Jack.md":{"path":"Characters/Jack.md","sha":null,"dirty":true,"justDownloaded":false,"lastModified":1745880934112,"deleted":true,"deletedAt":1745881021228},"Characters/Kev.md":{"path":"Characters/Kev.md","sha":null,"dirty":true,"justDownloaded":false,"lastModified":1745880947093,"deleted":true,"deletedAt":1745881013895},"Characters/Untitled 1.md":{"path":"Characters/Untitled 1.md","sha":null,"dirty":true,"justDownloaded":false,"lastModified":1745880950877,"deleted":true,"deletedAt":1745881011137},"Characters/Alex.md":{"path":"Characters/Alex.md","sha":null,"dirty":true,"justDownloaded":false,"lastModified":1745880957015,"deleted":true,"deletedAt":1745881016851},"Characters/Laurie -.md":{"path":"Characters/Laurie -.md","sha":null,"dirty":true,"justDownloaded":false,"lastModified":1745881011134},"Characters/Kev -.md":{"path":"Characters/Kev -.md","sha":null,"dirty":true,"justDownloaded":false,"lastModified":1745881013889},"Characters/Alex -.md":{"path":"Characters/Alex -.md","sha":null,"dirty":true,"justDownloaded":false,"lastModified":1745881016848},"Characters/Jack -.md":{"path":"Characters/Jack -.md","sha":null,"dirty":true,"justDownloaded":false,"lastModified":1745881021224}}}